web3_input_decoder/__init__.py
web3_input_decoder/decoder.py
web3_input_decoder/exceptions.py
web3_input_decoder/py.typed
web3_input_decoder/types.py
web3_input_decoder/utils/__init__.py
web3_input_decoder/utils/hex.py
web3_input_decoder/utils/parse.py
web3_input_decoder-0.1.15.dist-info/METADATA
web3_input_decoder-0.1.15.dist-info/WHEEL
web3_input_decoder-0.1.15.dist-info/licenses/LICENSE
web3_input_decoder-0.1.15.dist-info/RECORD
