Metadata-Version: 2.4
Name: web3-input-decoder
Version: 0.1.15
Summary: A simple offline web3 transaction input decoder for functions and constructors
License: MIT
License-File: LICENSE
Keywords: ethereum,web3
Author: Weiliang Li
Author-email: to.be.impressive@gmail.com
Maintainer: Weiliang Li
Maintainer-email: to.be.impressive@gmail.com
Requires-Python: >=3.9,<4.0
Classifier: Development Status :: 4 - Beta
Classifier: Intended Audience :: Developers
Classifier: License :: OSI Approved :: MIT License
Classifier: Natural Language :: English
Classifier: Operating System :: OS Independent
Classifier: Programming Language :: Python :: 3
Classifier: Programming Language :: Python :: 3.9
Classifier: Programming Language :: Python :: 3.10
Classifier: Programming Language :: Python :: 3.11
Classifier: Programming Language :: Python :: 3.12
Classifier: Programming Language :: Python :: 3.13
Classifier: Programming Language :: Python :: 3.14
Classifier: Programming Language :: Python :: Implementation :: CPython
Requires-Dist: eth-abi (>=5.0.1,<6.0.0)
Requires-Dist: eth-utils (>=2.0.0)
Requires-Dist: pycryptodome (>=3.18.0)
Requires-Dist: typing-extensions (>=4.5.0) ; python_version < "3.11"
Project-URL: Repository, https://github.com/kigawas/web3-input-decoder
